rockwall/__init__.py
rockwall-0.0.1.dist-info/METADATA
rockwall-0.0.1.dist-info/WHEEL
rockwall-0.0.1.dist-info/top_level.txt
rockwall-0.0.1.dist-info/RECORD
