Metadata-Version: 2.4
Name: rockwall
Version: 0.0.1
Summary: Rock-solid protection for AI-generated commands. Pre-execution safety validation for Claude Code and MCP servers.
Author-email: frmoretto <francesco.marinoni.moretto@gmail.com>
License: CC-BY-4.0
Project-URL: Homepage, https://github.com/frmoretto/rockwall
Project-URL: Repository, https://github.com/frmoretto/rockwall
Project-URL: Issues, https://github.com/frmoretto/rockwall/issues
Keywords: rockwall,ai-safety,command-validation,security,claude-code,mcp,pre-execution,clarity-gate,llm,bash,shell
Classifier: Development Status :: 1 - Planning
Classifier: Intended Audience :: Developers
Classifier: License :: OSI Approved
Classifier: Programming Language :: Python :: 3
Classifier: Programming Language :: Python :: 3.9
Classifier: Programming Language :: Python :: 3.10
Classifier: Programming Language :: Python :: 3.11
Classifier: Programming Language :: Python :: 3.12
Classifier: Topic :: Security
Classifier: Topic :: Software Development :: Quality Assurance
Requires-Python: >=3.9
